reykunyu_py/__init__.py
reykunyu_py/errors.py
reykunyu_py/reykunyu.py
reykunyu_py/util.py
reykunyu_py-0.1.5.dist-info/LICENSE
reykunyu_py-0.1.5.dist-info/METADATA
reykunyu_py-0.1.5.dist-info/WHEEL
reykunyu_py-0.1.5.dist-info/top_level.txt
reykunyu_py-0.1.5.dist-info/RECORD
