Metadata-Version: 2.1
Name: reykunyu-py
Version: 0.1.5
Summary: A Python wrapper for the Reykunyu API
Author: Conner "Nahura" McKay
Project-URL: Homepage, https://github.com/HappyHippo77/reykunyu-py
Project-URL: Issues, https://github.com/HappyHippo77/reykunyu-py/issues
Classifier: Programming Language :: Python :: 3
Classifier: License :: OSI Approved :: MIT License
Classifier: Operating System :: OS Independent
Requires-Python: >=3.8
License-File: LICENSE
Requires-Dist: requests
